{
"type": "FeatureCollection",
"name": "xyz_1075_1320_11",
"crs": { "type": "name", "properties": { "name": "urn:ogc:def:crs:OGC:1.3:CRS84" } },
"features": [
{ "type": "Feature", "properties": { "id": "2313", "amenity": "toilets", "changing_t": null, "descriptio": null, "fee": null, "hand_rail": null, "municipali": "Bellinzona", "name": null, "network": null, "stairs": null, "toilets_po": "seated", "wc_guide_i": "2313", "website": null, "wheelchair": null, "Cluster_ID": 43, "xyz": "1075_1320_11" }, "geometry": { "type": "Point", "coordinates": [ 9.033508, 46.193142 ] } },
{ "type": "Feature", "properties": { "id": "4709", "amenity": "toilets", "changing_t": null, "descriptio": null, "fee": null, "hand_rail": null, "municipali": "Bellinzona", "name": "Castello Bellinzona", "network": null, "stairs": null, "toilets_po": "seated", "wc_guide_i": "4709", "website": null, "wheelchair": null, "Cluster_ID": 43, "xyz": "1075_1320_11" }, "geometry": { "type": "Point", "coordinates": [ 9.023033, 46.192493 ] } },
{ "type": "Feature", "properties": { "id": "20212", "amenity": "toilets", "changing_t": null, "descriptio": null, "fee": null, "hand_rail": null, "municipali": "Bellinzona", "name": "Percorso Vita", "network": null, "stairs": null, "toilets_po": "seated", "wc_guide_i": "20212", "website": null, "wheelchair": null, "Cluster_ID": 43, "xyz": "1075_1320_11" }, "geometry": { "type": "Point", "coordinates": [ 9.01035, 46.193218 ] } }
]
}
