{
"type": "FeatureCollection",
"name": "xyz_1081_1325_11",
"crs": { "type": "name", "properties": { "name": "urn:ogc:def:crs:OGC:1.3:CRS84" } },
"features": [
{ "type": "Feature", "properties": { "id": "2292", "amenity": "toilets", "changing_t": null, "descriptio": null, "fee": null, "hand_rail": null, "municipali": "Susch", "name": "RHB Autoverlad Sagliains", "network": null, "stairs": null, "toilets_po": "seated", "wc_guide_i": "2292", "website": null, "wheelchair": null, "Cluster_ID": 47, "xyz": "1081_1325_11" }, "geometry": { "type": "Point", "coordinates": [ 10.096328, 46.763451 ] } },
{ "type": "Feature", "properties": { "id": "3925", "amenity": "toilets", "changing_t": null, "descriptio": null, "fee": null, "hand_rail": null, "municipali": "Schweiz", "name": "Staziun RHB", "network": null, "stairs": null, "toilets_po": "seated", "wc_guide_i": "3925", "website": null, "wheelchair": null, "Cluster_ID": 47, "xyz": "1081_1325_11" }, "geometry": { "type": "Point", "coordinates": [ 10.113986, 46.775558 ] } },
{ "type": "Feature", "properties": { "id": "19436", "amenity": "toilets", "changing_t": null, "descriptio": null, "fee": null, "hand_rail": null, "municipali": "Zernez", "name": "RHB Bahnhof Zernez", "network": null, "stairs": null, "toilets_po": "seated", "wc_guide_i": "19436", "website": null, "wheelchair": null, "Cluster_ID": 47, "xyz": "1081_1325_11" }, "geometry": { "type": "Point", "coordinates": [ 10.089956, 46.69817 ] } }
]
}
