{
"type": "FeatureCollection",
"name": "xyz_1075_1318_11",
"crs": { "type": "name", "properties": { "name": "urn:ogc:def:crs:OGC:1.3:CRS84" } },
"features": [
{ "type": "Feature", "properties": { "id": "3924", "amenity": "toilets", "changing_t": null, "descriptio": null, "fee": null, "hand_rail": null, "municipali": "Mendrisio", "name": "A2 - dir. Nord", "network": null, "stairs": null, "toilets_po": "seated", "wc_guide_i": "3924", "website": null, "wheelchair": null, "Cluster_ID": 25, "xyz": "1075_1318_11" }, "geometry": { "type": "Point", "coordinates": [ 8.976519, 45.893951 ] } }
]
}
