{
"type": "FeatureCollection",
"name": "xyz_1072_1333_11",
"crs": { "type": "name", "properties": { "name": "urn:ogc:def:crs:OGC:1.3:CRS84" } },
"features": [
{ "type": "Feature", "properties": { "id": "2140", "amenity": "toilets", "changing_t": null, "descriptio": "Freundlich Fragen oder Konsumation", "fee": null, "hand_rail": null, "municipali": "Neuhausen am Rheinfall", "name": "Tankstelle", "network": null, "stairs": null, "toilets_po": "seated", "wc_guide_i": "2140", "website": null, "wheelchair": null, "Cluster_ID": 42, "xyz": "1072_1333_11" }, "geometry": { "type": "Point", "coordinates": [ 8.611393, 47.686642 ] } },
{ "type": "Feature", "properties": { "id": "2408", "amenity": "toilets", "changing_t": null, "descriptio": null, "fee": null, "hand_rail": null, "municipali": "Neunkirch", "name": "Bahnhof DB", "network": null, "stairs": null, "toilets_po": "seated", "wc_guide_i": "2408", "website": null, "wheelchair": null, "Cluster_ID": 42, "xyz": "1072_1333_11" }, "geometry": { "type": "Point", "coordinates": [ 8.494878, 47.689377 ] } },
{ "type": "Feature", "properties": { "id": "16593", "amenity": "toilets", "changing_t": null, "descriptio": null, "fee": null, "hand_rail": null, "municipali": "Neuhausen am Rheinfall", "name": "BP Tankstelle", "network": null, "stairs": null, "toilets_po": "seated", "wc_guide_i": "16593", "website": null, "wheelchair": null, "Cluster_ID": 42, "xyz": "1072_1333_11" }, "geometry": { "type": "Point", "coordinates": [ 8.612136, 47.684261 ] } }
]
}
