{
"type": "FeatureCollection",
"name": "xyz_1076_1329_11",
"crs": { "type": "name", "properties": { "name": "urn:ogc:def:crs:OGC:1.3:CRS84" } },
"features": [
{ "type": "Feature", "properties": { "id": "1802", "amenity": "toilets", "changing_t": null, "descriptio": null, "fee": null, "hand_rail": null, "municipali": "Krummenau", "name": "Bahnhof", "network": null, "stairs": null, "toilets_po": "seated", "wc_guide_i": "1802", "website": null, "wheelchair": null, "Cluster_ID": 1, "xyz": "1076_1329_11" }, "geometry": { "type": "Point", "coordinates": [ 9.167919, 47.248859 ] } },
{ "type": "Feature", "properties": { "id": "2296", "amenity": "toilets", "changing_t": null, "descriptio": null, "fee": null, "hand_rail": null, "municipali": "Nesslau", "name": "Bahnhof", "network": null, "stairs": null, "toilets_po": "seated", "wc_guide_i": "2296", "website": null, "wheelchair": null, "Cluster_ID": 1, "xyz": "1076_1329_11" }, "geometry": { "type": "Point", "coordinates": [ 9.197463, 47.226719 ] } },
{ "type": "Feature", "properties": { "id": "3401", "amenity": "toilets", "changing_t": null, "descriptio": null, "fee": null, "hand_rail": null, "municipali": "Stein 9655", "name": "Gemeindehaus", "network": null, "stairs": null, "toilets_po": "seated", "wc_guide_i": "3401", "website": null, "wheelchair": null, "Cluster_ID": 1, "xyz": "1076_1329_11" }, "geometry": { "type": "Point", "coordinates": [ 9.226655, 47.200294 ] } }
]
}
