{
"type": "FeatureCollection",
"name": "xyz_1079_1330_11",
"crs": { "type": "name", "properties": { "name": "urn:ogc:def:crs:OGC:1.3:CRS84" } },
"features": [
{ "type": "Feature", "properties": { "id": "19781", "amenity": "toilets", "changing_t": null, "descriptio": null, "fee": null, "hand_rail": null, "municipali": "Hohenems", "name": null, "network": null, "stairs": null, "toilets_po": "seated", "wc_guide_i": "19781", "website": null, "wheelchair": null, "Cluster_ID": 29, "xyz": "1079_1330_11" }, "geometry": { "type": "Point", "coordinates": [ 9.67738, 47.3736 ] } },
{ "type": "Feature", "properties": { "id": "21127", "amenity": "toilets", "changing_t": null, "descriptio": null, "fee": null, "hand_rail": null, "municipali": "Diepoldsau", "name": "Sportanlage", "network": null, "stairs": null, "toilets_po": "seated", "wc_guide_i": "21127", "website": null, "wheelchair": null, "Cluster_ID": 29, "xyz": "1079_1330_11" }, "geometry": { "type": "Point", "coordinates": [ 9.670232, 47.382385 ] } }
]
}
