{
"type": "FeatureCollection",
"name": "xyz_1078_1322_11",
"crs": { "type": "name", "properties": { "name": "urn:ogc:def:crs:OGC:1.3:CRS84" } },
"features": [
{ "type": "Feature", "properties": { "id": "1584", "amenity": "toilets", "changing_t": null, "descriptio": null, "fee": null, "hand_rail": null, "municipali": "Vicosoprano", "name": null, "network": null, "stairs": null, "toilets_po": "seated", "wc_guide_i": "1584", "website": null, "wheelchair": null, "Cluster_ID": 32, "xyz": "1078_1322_11" }, "geometry": { "type": "Point", "coordinates": [ 9.619657, 46.350159 ] } }
]
}
